st_llm_search_engine/.DS_Store
st_llm_search_engine/__init__.py
st_llm_search_engine/_server.py
st_llm_search_engine/st_llm_search_engine.py
st_llm_search_engine/utils.py
st_llm_search_engine/frontend/package-lock.json
st_llm_search_engine/frontend/package.json
st_llm_search_engine/frontend/tsconfig.json
st_llm_search_engine/frontend/typings.d.ts
st_llm_search_engine/frontend/webpack.config.js
st_llm_search_engine/frontend/build/index.html
st_llm_search_engine/frontend/build/static/js/main.js
st_llm_search_engine/frontend/build/static/js/main.js.LICENSE.txt
st_llm_search_engine/frontend/public/index.html
st_llm_search_engine/frontend/src/index.tsx
st_llm_search_engine/frontend/src/test_index.tsx
st_llm_search_engine/frontend/src/typings.d.ts
st_llm_search_engine/frontend/src/assets/filter-icon.svg
st_llm_search_engine/frontend/src/assets/setting-icon.svg
st_llm_search_engine/frontend/src/components/ButtonGroup.tsx
st_llm_search_engine/frontend/src/components/ChatPage.tsx
st_llm_search_engine/frontend/src/components/ConfirmModal.tsx
st_llm_search_engine/frontend/src/components/IconButton.tsx
st_llm_search_engine/frontend/src/components/LoadingModal.tsx
st_llm_search_engine/frontend/src/components/Sidebar.tsx
st_llm_search_engine/frontend/src/components/SidebarHeader.tsx
st_llm_search_engine/frontend/src/components/ChatPage/index.tsx
st_llm_search_engine/frontend/src/components/ChatPage/components/ErrorMessage.tsx
st_llm_search_engine/frontend/src/components/ChatPage/components/MessageInput.tsx
st_llm_search_engine/frontend/src/components/ChatPage/components/MessageItem.tsx
st_llm_search_engine/frontend/src/components/ChatPage/components/MessageList.tsx
st_llm_search_engine/frontend/src/components/ChatPage/components/SavedSearchExecution.tsx
st_llm_search_engine/frontend/src/components/ChatPage/components/TableRenderer.tsx
st_llm_search_engine/frontend/src/components/ChatPage/components/ThinkingIndicator.tsx
st_llm_search_engine-0.6.0.dist-info/LICENSE
st_llm_search_engine-0.6.0.dist-info/METADATA
st_llm_search_engine-0.6.0.dist-info/WHEEL
st_llm_search_engine-0.6.0.dist-info/entry_points.txt
st_llm_search_engine-0.6.0.dist-info/RECORD
