Metadata-Version: 2.3
Name: st-llm-search-engine
Version: 0.6.0
Summary: A Streamlit component enabling LLM-driven semantic search and data retrieval.
License: MIT
Author: Pei-Hsuan Huang
Author-email: patrick501004123854@gmail.com
Requires-Python: >=3.10,<4
Classifier: Development Status :: 3 - Alpha
Classifier: Intended Audience :: Developers
Classifier: License :: OSI Approved :: MIT License
Classifier: Programming Language :: Python :: 3
Classifier: Programming Language :: Python :: 3.10
Classifier: Programming Language :: Python :: 3.11
Classifier: Programming Language :: Python :: 3.12
Classifier: Programming Language :: Python :: 3.13
Requires-Dist: concurrent-log-handler (>=0.9.26,<0.10.0)
Requires-Dist: faker (>=37.3.0,<38.0.0)
Requires-Dist: fakeredis (>=2.29.0,<3.0.0)
Requires-Dist: fastapi (>=0.115.12,<0.116.0)
Requires-Dist: google-auth (>=2.40.1,<3.0.0)
Requires-Dist: google-generativeai (>=0.8.5,<0.9.0)
Requires-Dist: gspread (>=6.2.1,<7.0.0)
Requires-Dist: pandas (>=2.2.3,<3.0.0)
Requires-Dist: pytest (>=8.3.5,<9.0.0)
Requires-Dist: pytest-mock (>=3.14.0,<4.0.0)
Requires-Dist: redis (>=6.1.0,<7.0.0)
Requires-Dist: requests (>=2.32.3,<3.0.0)
Requires-Dist: streamlit (>=1.45.1,<2.0.0)
Requires-Dist: uvicorn (>=0.34.2,<0.35.0)
Project-URL: bugs, https://github.com/chips-fries/st_llm_search_engine/issues
Project-URL: changelog, https://github.com/chips-fries/st_llm_search_engine/blob/master/changelog.md
Project-URL: homepage, https://github.com/chips-fries/st_llm_search_engine
